R2S2/R2S2.py
R2S2/__init__.py
R2S2/lte440.bsp
R2S2/lte440.tpc
r2s2-0.1.0.dist-info/METADATA
r2s2-0.1.0.dist-info/WHEEL
r2s2-0.1.0.dist-info/top_level.txt
r2s2-0.1.0.dist-info/RECORD
