Metadata-Version: 2.4
Name: r2s2
Version: 0.1.0
Summary: Tools for calculating the coordinate transformation between the Earth-Moon space-time reference systems.
Author-email: Zhang Jing <jingzhang@pmo.ac.cn>, Lu Xu <luxu@pmo.ac.cn>
License-Expression: GPL-3.0-or-later
Requires-Dist: numpy
Requires-Dist: calcephpy
